{
  "dcOrderResponseList": [
    {
      "estimatedDelivery": "2021-03-07",
      "dcOrderList": [
        {
          "orderStatus": "delivered",
          "estimatedDelivery": "2021-03-07",
          "orderOn": "2021-03-08",
          "palletCount": "28",
          "routeCd": "1009",
          "totalUnits": "3111",
          "distributionCentre": "33",
          "dcName": "Auburn",
          "numberOfStops": "6"
        },
        {
          "orderStatus": "delivered",
          "estimatedDelivery": "2021-03-07",
          "orderOn": "2021-03-08",
          "palletCount": "33",
          "routeCd": "1023",
          "totalUnits": "3599",
          "distributionCentre": "33",
          "dcName": "Auburn",
          "numberOfStops": "7"
        },
        {
          "orderStatus": "delivered",
          "estimatedDelivery": "2021-03-07",
          "orderOn": "2021-03-08",
          "palletCount": "24",
          "routeCd": "1112",
          "totalUnits": "3044",
          "distributionCentre": "33",
          "dcName": "Auburn",
          "numberOfStops": "6"
        },
        {
          "orderStatus": "delivered",
          "estimatedDelivery": "2021-03-07",
          "orderOn": "2021-03-08",
          "palletCount": "14",
          "routeCd": "1113",
          "totalUnits": "2816",
          "distributionCentre": "33",
          "dcName": "Auburn",
          "numberOfStops": "1"
        },
        {
          "orderStatus": "delivered",
          "estimatedDelivery": "2021-03-07",
          "orderOn": "2021-03-08",
          "palletCount": "18",
          "routeCd": "1114",
          "totalUnits": "2238",
          "distributionCentre": "33",
          "dcName": "Auburn",
          "numberOfStops": "3"
        },
        {
          "orderStatus": "delivered",
          "estimatedDelivery": "2021-03-07",
          "orderOn": "2021-03-08",
          "palletCount": "13",
          "routeCd": "1121",
          "totalUnits": "2510",
          "distributionCentre": "33",
          "dcName": "Auburn",
          "numberOfStops": "4"
        },
        {
          "orderStatus": "delivered",
          "estimatedDelivery": "2021-03-07",
          "orderOn": "2021-03-08",
          "palletCount": "17",
          "routeCd": "1122",
          "totalUnits": "3023",
          "distributionCentre": "33",
          "dcName": "Auburn",
          "numberOfStops": "3"
        },
        {
          "orderStatus": "delivered",
          "estimatedDelivery": "2021-03-07",
          "orderOn": "2021-03-08",
          "palletCount": "28",
          "routeCd": "1123",
          "totalUnits": "2696",
          "distributionCentre": "33",
          "dcName": "Auburn",
          "numberOfStops": "3"
        },
        {
          "orderStatus": "delivered",
          "estimatedDelivery": "2021-03-07",
          "orderOn": "2021-03-08",
          "palletCount": "25",
          "routeCd": "1124",
          "totalUnits": "1274",
          "distributionCentre": "33",
          "dcName": "Auburn",
          "numberOfStops": "6"
        },
        {
          "orderStatus": "delivered",
          "estimatedDelivery": "2021-03-07",
          "orderOn": "2021-03-08",
          "palletCount": "19",
          "routeCd": "1125",
          "totalUnits": "3235",
          "distributionCentre": "33",
          "dcName": "Auburn",
          "numberOfStops": "4"
        },
        {
          "orderStatus": "delivered",
          "estimatedDelivery": "2021-03-07",
          "orderOn": "2021-03-08",
          "palletCount": "26",
          "routeCd": "1126",
          "totalUnits": "3779",
          "distributionCentre": "33",
          "dcName": "Auburn",
          "numberOfStops": "6"
        },
        {
          "orderStatus": "delivered",
          "estimatedDelivery": "2021-03-07",
          "orderOn": "2021-03-08",
          "palletCount": "19",
          "routeCd": "1127",
          "totalUnits": "2431",
          "distributionCentre": "33",
          "dcName": "Auburn",
          "numberOfStops": "2"
        },
        {
          "orderStatus": "delivered",
          "estimatedDelivery": "2021-03-07",
          "orderOn": "2021-03-08",
          "palletCount": "24",
          "routeCd": "1134",
          "totalUnits": "3405",
          "distributionCentre": "33",
          "dcName": "Auburn",
          "numberOfStops": "5"
        },
        {
          "orderStatus": "delivered",
          "estimatedDelivery": "2021-03-07",
          "orderOn": "2021-03-08",
          "palletCount": "27",
          "routeCd": "7415",
          "totalUnits": "2226",
          "distributionCentre": "33",
          "dcName": "Auburn",
          "numberOfStops": "2"
        },
        {
          "orderStatus": "delivered",
          "estimatedDelivery": "2021-03-07",
          "orderOn": "2021-03-08",
          "palletCount": "27",
          "routeCd": "7416",
          "totalUnits": "2996",
          "distributionCentre": "33",
          "dcName": "Auburn",
          "numberOfStops": "3"
        },
        {
          "orderStatus": "delivered",
          "estimatedDelivery": "2021-03-07",
          "orderOn": "2021-03-08",
          "palletCount": "31",
          "routeCd": "7425",
          "totalUnits": "3026",
          "distributionCentre": "33",
          "dcName": "Auburn",
          "numberOfStops": "3"
        },
        {
          "orderStatus": "delivered",
          "estimatedDelivery": "2021-03-07",
          "orderOn": "2021-03-08",
          "palletCount": "30",
          "routeCd": "7442",
          "totalUnits": "2715",
          "distributionCentre": "33",
          "dcName": "Auburn",
          "numberOfStops": "3"
        },
        {
          "orderStatus": "delivered",
          "estimatedDelivery": "2021-03-07",
          "orderOn": "2021-03-08",
          "palletCount": "28",
          "routeCd": "7443",
          "totalUnits": "3018",
          "distributionCentre": "33",
          "dcName": "Auburn",
          "numberOfStops": "3"
        },
        {
          "orderStatus": "delivered",
          "estimatedDelivery": "2021-03-07",
          "orderOn": "2021-03-08",
          "palletCount": "29",
          "routeCd": "7444",
          "totalUnits": "2850",
          "distributionCentre": "33",
          "dcName": "Auburn",
          "numberOfStops": "4"
        },
        {
          "orderStatus": "intransit",
          "estimatedDelivery": "2021-03-07",
          "orderOn": "2021-03-08",
          "palletCount": "22",
          "routeCd": "1108",
          "totalUnits": "3008",
          "distributionCentre": "33",
          "dcName": "Auburn",
          "numberOfStops": "3"
        }
      ]
    },
    {
      "estimatedDelivery": "2021-03-08",
      "dcOrderList": [
        {
          "orderStatus": "delivered",
          "estimatedDelivery": "2021-03-08",
          "orderOn": "2021-03-08",
          "palletCount": "11",
          "routeCd": "1401",
          "totalUnits": "1187",
          "distributionCentre": "33",
          "dcName": "Auburn",
          "numberOfStops": "2"
        },
        {
          "orderStatus": "delivered",
          "estimatedDelivery": "2021-03-08",
          "orderOn": "2021-03-08",
          "palletCount": "25",
          "routeCd": "1402",
          "totalUnits": "2301",
          "distributionCentre": "33",
          "dcName": "Auburn",
          "numberOfStops": "2"
        },
        {
          "orderStatus": "delivered",
          "estimatedDelivery": "2021-03-08",
          "orderOn": "2021-03-08",
          "palletCount": "30",
          "routeCd": "1403",
          "totalUnits": "2377",
          "distributionCentre": "33",
          "dcName": "Auburn",
          "numberOfStops": "3"
        },
        {
          "orderStatus": "delivered",
          "estimatedDelivery": "2021-03-08",
          "orderOn": "2021-03-08",
          "palletCount": "31",
          "routeCd": "1404",
          "totalUnits": "2041",
          "distributionCentre": "33",
          "dcName": "Auburn",
          "numberOfStops": "5"
        },
        {
          "orderStatus": "delivered",
          "estimatedDelivery": "2021-03-08",
          "orderOn": "2021-03-08",
          "palletCount": "29",
          "routeCd": "1406",
          "totalUnits": "2928",
          "distributionCentre": "33",
          "dcName": "Auburn",
          "numberOfStops": "2"
        },
        {
          "orderStatus": "delivered",
          "estimatedDelivery": "2021-03-08",
          "orderOn": "2021-03-08",
          "palletCount": "18",
          "routeCd": "1407",
          "totalUnits": "1543",
          "distributionCentre": "33",
          "dcName": "Auburn",
          "numberOfStops": "2"
        },
        {
          "orderStatus": "delivered",
          "estimatedDelivery": "2021-03-08",
          "orderOn": "2021-03-08",
          "palletCount": "18",
          "routeCd": "1408",
          "totalUnits": "1669",
          "distributionCentre": "33",
          "dcName": "Auburn",
          "numberOfStops": "2"
        },
        {
          "orderStatus": "delivered",
          "estimatedDelivery": "2021-03-08",
          "orderOn": "2021-03-08",
          "palletCount": "21",
          "routeCd": "1411",
          "totalUnits": "1534",
          "distributionCentre": "33",
          "dcName": "Auburn",
          "numberOfStops": "4"
        },
        {
          "orderStatus": "delivered",
          "estimatedDelivery": "2021-03-08",
          "orderOn": "2021-03-08",
          "palletCount": "16",
          "routeCd": "1412",
          "totalUnits": "1631",
          "distributionCentre": "33",
          "dcName": "Auburn",
          "numberOfStops": "2"
        },
        {
          "orderStatus": "delivered",
          "estimatedDelivery": "2021-03-08",
          "orderOn": "2021-03-08",
          "palletCount": "28",
          "routeCd": "1413",
          "totalUnits": "2351",
          "distributionCentre": "33",
          "dcName": "Auburn",
          "numberOfStops": "4"
        },
        {
          "orderStatus": "delivered",
          "estimatedDelivery": "2021-03-08",
          "orderOn": "2021-03-08",
          "palletCount": "24",
          "routeCd": "1415",
          "totalUnits": "1927",
          "distributionCentre": "33",
          "dcName": "Auburn",
          "numberOfStops": "3"
        },
        {
          "orderStatus": "delivered",
          "estimatedDelivery": "2021-03-08",
          "orderOn": "2021-03-08",
          "palletCount": "29",
          "routeCd": "1416",
          "totalUnits": "2597",
          "distributionCentre": "33",
          "dcName": "Auburn",
          "numberOfStops": "2"
        },
        {
          "orderStatus": "delivered",
          "estimatedDelivery": "2021-03-08",
          "orderOn": "2021-03-08",
          "palletCount": "25",
          "routeCd": "1417",
          "totalUnits": "2065",
          "distributionCentre": "33",
          "dcName": "Auburn",
          "numberOfStops": "4"
        },
        {
          "orderStatus": "delivered",
          "estimatedDelivery": "2021-03-08",
          "orderOn": "2021-03-08",
          "palletCount": "21",
          "routeCd": "1418",
          "totalUnits": "2038",
          "distributionCentre": "33",
          "dcName": "Auburn",
          "numberOfStops": "2"
        },
        {
          "orderStatus": "delivered",
          "estimatedDelivery": "2021-03-08",
          "orderOn": "2021-03-08",
          "palletCount": "20",
          "routeCd": "1419",
          "totalUnits": "1512",
          "distributionCentre": "33",
          "dcName": "Auburn",
          "numberOfStops": "2"
        },
        {
          "orderStatus": "delivered",
          "estimatedDelivery": "2021-03-08",
          "orderOn": "2021-03-08",
          "palletCount": "14",
          "routeCd": "1420",
          "totalUnits": "1376",
          "distributionCentre": "33",
          "dcName": "Auburn",
          "numberOfStops": "1"
        },
        {
          "orderStatus": "delivered",
          "estimatedDelivery": "2021-03-08",
          "orderOn": "2021-03-08",
          "palletCount": "18",
          "routeCd": "1421",
          "totalUnits": "1724",
          "distributionCentre": "33",
          "dcName": "Auburn",
          "numberOfStops": "2"
        },
        {
          "orderStatus": "delivered",
          "estimatedDelivery": "2021-03-08",
          "orderOn": "2021-03-08",
          "palletCount": "18",
          "routeCd": "1422",
          "totalUnits": "1836",
          "distributionCentre": "33",
          "dcName": "Auburn",
          "numberOfStops": "3"
        },
        {
          "orderStatus": "intransit",
          "estimatedDelivery": "2021-03-08",
          "orderOn": "2021-03-08",
          "palletCount": "28",
          "routeCd": "1405",
          "totalUnits": "2177",
          "distributionCentre": "33",
          "dcName": "Auburn",
          "numberOfStops": "7"
        },
        {
          "orderStatus": "intransit",
          "estimatedDelivery": "2021-03-08",
          "orderOn": "2021-03-08",
          "palletCount": "27",
          "routeCd": "1409",
          "totalUnits": "2266",
          "distributionCentre": "33",
          "dcName": "Auburn",
          "numberOfStops": "5"
        },
        {
          "orderStatus": "intransit",
          "estimatedDelivery": "2021-03-08",
          "orderOn": "2021-03-08",
          "palletCount": "27",
          "routeCd": "1410",
          "totalUnits": "2785",
          "distributionCentre": "33",
          "dcName": "Auburn",
          "numberOfStops": "2"
        },
        {
          "orderStatus": "intransit",
          "estimatedDelivery": "2021-03-08",
          "orderOn": "2021-03-08",
          "palletCount": "13",
          "routeCd": "1414",
          "totalUnits": "989",
          "distributionCentre": "33",
          "dcName": "Auburn",
          "numberOfStops": "1"
        },
        {
          "orderStatus": "intransit",
          "estimatedDelivery": "2021-03-08",
          "orderOn": "2021-03-08",
          "palletCount": "20",
          "routeCd": "1424",
          "totalUnits": "1899",
          "distributionCentre": "33",
          "dcName": "Auburn",
          "numberOfStops": "2"
        },
        {
          "orderStatus": "intransit",
          "estimatedDelivery": "2021-03-08",
          "orderOn": "2021-03-08",
          "palletCount": "27",
          "routeCd": "1425",
          "totalUnits": "2152",
          "distributionCentre": "33",
          "dcName": "Auburn",
          "numberOfStops": "2"
        },
        {
          "orderStatus": "intransit",
          "estimatedDelivery": "2021-03-08",
          "orderOn": "2021-03-08",
          "palletCount": "29",
          "routeCd": "1426",
          "totalUnits": "2524",
          "distributionCentre": "33",
          "dcName": "Auburn",
          "numberOfStops": "4"
        },
        {
          "orderStatus": "intransit",
          "estimatedDelivery": "2021-03-08",
          "orderOn": "2021-03-08",
          "palletCount": "27",
          "routeCd": "1427",
          "totalUnits": "2549",
          "distributionCentre": "33",
          "dcName": "Auburn",
          "numberOfStops": "2"
        },
        {
          "orderStatus": "intransit",
          "estimatedDelivery": "2021-03-08",
          "orderOn": "2021-03-08",
          "palletCount": "26",
          "routeCd": "1428",
          "totalUnits": "2311",
          "distributionCentre": "33",
          "dcName": "Auburn",
          "numberOfStops": "2"
        },
        {
          "orderStatus": "intransit",
          "estimatedDelivery": "2021-03-08",
          "orderOn": "2021-03-08",
          "palletCount": "13",
          "routeCd": "1429",
          "totalUnits": "1344",
          "distributionCentre": "33",
          "dcName": "Auburn",
          "numberOfStops": "1"
        },
        {
          "orderStatus": "intransit",
          "estimatedDelivery": "2021-03-08",
          "orderOn": "2021-03-08",
          "palletCount": "23",
          "routeCd": "1430",
          "totalUnits": "1876",
          "distributionCentre": "33",
          "dcName": "Auburn",
          "numberOfStops": "3"
        },
        {
          "orderStatus": "intransit",
          "estimatedDelivery": "2021-03-08",
          "orderOn": "2021-03-08",
          "palletCount": "30",
          "routeCd": "1431",
          "totalUnits": "2193",
          "distributionCentre": "33",
          "dcName": "Auburn",
          "numberOfStops": "5"
        },
        {
          "orderStatus": "intransit",
          "estimatedDelivery": "2021-03-08",
          "orderOn": "2021-03-08",
          "palletCount": "25",
          "routeCd": "1432",
          "totalUnits": "2054",
          "distributionCentre": "33",
          "dcName": "Auburn",
          "numberOfStops": "3"
        },
        {
          "orderStatus": "intransit",
          "estimatedDelivery": "2021-03-08",
          "orderOn": "2021-03-08",
          "palletCount": "26",
          "routeCd": "1433",
          "totalUnits": "2038",
          "distributionCentre": "33",
          "dcName": "Auburn",
          "numberOfStops": "4"
        },
        {
          "orderStatus": "intransit",
          "estimatedDelivery": "2021-03-08",
          "orderOn": "2021-03-08",
          "palletCount": "28",
          "routeCd": "1434",
          "totalUnits": "2673",
          "distributionCentre": "33",
          "dcName": "Auburn",
          "numberOfStops": "2"
        },
        {
          "orderStatus": "intransit",
          "estimatedDelivery": "2021-03-08",
          "orderOn": "2021-03-08",
          "palletCount": "29",
          "routeCd": "1435",
          "totalUnits": "2804",
          "distributionCentre": "33",
          "dcName": "Auburn",
          "numberOfStops": "2"
        },
        {
          "orderStatus": "intransit",
          "estimatedDelivery": "2021-03-08",
          "orderOn": "2021-03-08",
          "palletCount": "26",
          "routeCd": "1437",
          "totalUnits": "768",
          "distributionCentre": "33",
          "dcName": "Auburn",
          "numberOfStops": "3"
        },
        {
          "orderStatus": "intransit",
          "estimatedDelivery": "2021-03-08",
          "orderOn": "2021-03-08",
          "palletCount": "17",
          "routeCd": "1438",
          "totalUnits": "884",
          "distributionCentre": "33",
          "dcName": "Auburn",
          "numberOfStops": "4"
        },
        {
          "orderStatus": "intransit",
          "estimatedDelivery": "2021-03-08",
          "orderOn": "2021-03-08",
          "palletCount": "10",
          "routeCd": "1439",
          "totalUnits": "198",
          "distributionCentre": "33",
          "dcName": "Auburn",
          "numberOfStops": "3"
        },
        {
          "orderStatus": "intransit",
          "estimatedDelivery": "2021-03-08",
          "orderOn": "2021-03-08",
          "palletCount": "24",
          "routeCd": "1440",
          "totalUnits": "575",
          "distributionCentre": "33",
          "dcName": "Auburn",
          "numberOfStops": "4"
        },
        {
          "orderStatus": "intransit",
          "estimatedDelivery": "2021-03-08",
          "orderOn": "2021-03-08",
          "palletCount": "17",
          "routeCd": "1441",
          "totalUnits": "721",
          "distributionCentre": "33",
          "dcName": "Auburn",
          "numberOfStops": "4"
        },
        {
          "orderStatus": "intransit",
          "estimatedDelivery": "2021-03-08",
          "orderOn": "2021-03-08",
          "palletCount": "28",
          "routeCd": "1442",
          "totalUnits": "592",
          "distributionCentre": "33",
          "dcName": "Auburn",
          "numberOfStops": "2"
        },
        {
          "orderStatus": "intransit",
          "estimatedDelivery": "2021-03-08",
          "orderOn": "2021-03-08",
          "palletCount": "24",
          "routeCd": "1443",
          "totalUnits": "850",
          "distributionCentre": "33",
          "dcName": "Auburn",
          "numberOfStops": "2"
        },
        {
          "orderStatus": "intransit",
          "estimatedDelivery": "2021-03-08",
          "orderOn": "2021-03-08",
          "palletCount": "8",
          "routeCd": "1444",
          "totalUnits": "198",
          "distributionCentre": "33",
          "dcName": "Auburn",
          "numberOfStops": "3"
        },
        {
          "orderStatus": "intransit",
          "estimatedDelivery": "2021-03-08",
          "orderOn": "2021-03-08",
          "palletCount": "23",
          "routeCd": "1446",
          "totalUnits": "675",
          "distributionCentre": "33",
          "dcName": "Auburn",
          "numberOfStops": "3"
        },
        {
          "orderStatus": "intransit",
          "estimatedDelivery": "2021-03-08",
          "orderOn": "2021-03-08",
          "palletCount": "22",
          "routeCd": "1447",
          "totalUnits": "771",
          "distributionCentre": "33",
          "dcName": "Auburn",
          "numberOfStops": "3"
        }
      ]
    }
  ]
}
