{"orderRouteInfoList":[{"stopID":"0","storeID":"05-DC","status":"Completed","estimatedArrival":null,"estimatedDeparture":"2021-03-07T07:26:00.000+00:00","actualArrivalTime":null,"actualDepartureTime":"2021-03-07T07:26:00.000+00:00","latitude":null,"longitude":null,"actualArrivalTimeText":null,"actualDepartureTimeText":null,"storePhone":null,"address":null},{"stopID":"1","storeID":"0010","status":"Delivered","estimatedArrival":"2021-03-07T08:08:00.000+00:00","estimatedDeparture":"2021-03-07T08:30:00.000+00:00","actualArrivalTime":"2021-03-07T08:25:00.000+00:00","actualDepartureTime":"2021-03-07T08:50:00.000+00:00","latitude":"39.6458799","longitude":"-105.3401659","actualArrivalTimeText":null,"actualDepartureTimeText":null,"storePhone":"303-674-6625","address":"3851 S Hwy 74"},{"stopID":"2","storeID":"2792","status":"Delivered","estimatedArrival":"2021-03-07T09:05:00.000+00:00","estimatedDeparture":"2021-03-07T09:20:00.000+00:00","actualArrivalTime":"2021-03-07T09:48:00.000+00:00","actualDepartureTime":"2021-03-07T10:01:00.000+00:00","latitude":"39.5272894","longitude":"-105.3033215","actualArrivalTimeText":null,"actualDepartureTimeText":null,"storePhone":"303-838-4375","address":"27152 Main St"},{"stopID":"3","storeID":"1548","status":"Delivered","estimatedArrival":"2021-03-07T10:09:00.000+00:00","estimatedDeparture":"2021-03-07T10:29:00.000+00:00","actualArrivalTime":"2021-03-07T10:50:00.000+00:00","actualDepartureTime":"2021-03-07T11:07:00.000+00:00","latitude":"39.5376429","longitude":"-104.8832633","actualArrivalTimeText":null,"actualDepartureTimeText":null,"storePhone":"303-649-9111","address":"9229 E Lincoln Ave"},{"stopID":"4","storeID":"1446","status":"Delivered","estimatedArrival":"2021-03-07T10:43:00.000+00:00","estimatedDeparture":"2021-03-07T11:10:00.000+00:00","actualArrivalTime":"2021-03-07T11:30:00.000+00:00","actualDepartureTime":"2021-03-07T11:38:00.000+00:00","latitude":"39.5160731","longitude":"-104.7664971","actualArrivalTimeText":null,"actualDepartureTimeText":null,"storePhone":"303-840-1604","address":"11051 S Parker Rd"},{"stopID":"5","storeID":"05-DC","status":"Delivered","estimatedArrival":"2021-03-07T11:43:00.000+00:00","estimatedDeparture":null,"actualArrivalTime":"2021-03-07T12:15:00.000+00:00","actualDepartureTime":null,"latitude":null,"longitude":null,"actualArrivalTimeText":null,"actualDepartureTimeText":null,"storePhone":null,"address":null}],"tripInfo":null,"vehicleInfo":null}